{
  "accuracy_matrix": [
    [
      0.9364,
      0.0,
      0.0,
      0.0,
      0.0,
      0.0,
      0.0,
      0.0,
      0.0,
      0.0
    ],
    [
      0.8765,
      0.9375,
      0.0,
      0.0,
      0.0,
      0.0,
      0.0,
      0.0,
      0.0,
      0.0
    ],
    [
      0.5529,
      0.7945,
      0.9519,
      0.0,
      0.0,
      0.0,
      0.0,
      0.0,
      0.0,
      0.0
    ],
    [
      0.4022,
      0.6957,
      0.8586,
      0.9461,
      0.0,
      0.0,
      0.0,
      0.0,
      0.0,
      0.0
    ],
    [
      0.3261,
      0.4541,
      0.7636,
      0.8956,
      0.9565,
      0.0,
      0.0,
      0.0,
      0.0,
      0.0
    ],
    [
      0.3034,
      0.3701,
      0.5742,
      0.7703,
      0.9294,
      0.9525,
      0.0,
      0.0,
      0.0,
      0.0
    ],
    [
      0.1957,
      0.193,
      0.3588,
      0.5081,
      0.7726,
      0.8824,
      0.9573,
      0.0,
      0.0,
      0.0
    ],
    [
      0.132,
      0.1657,
      0.1754,
      0.2978,
      0.4732,
      0.655,
      0.8566,
      0.9504,
      0.0,
      0.0
    ],
    [
      0.1075,
      0.1198,
      0.1275,
      0.2245,
      0.2988,
      0.3798,
      0.6444,
      0.8642,
      0.9624,
      0.0
    ],
    [
      0.0794,
      0.0865,
      0.0746,
      0.1869,
      0.2213,
      0.2868,
      0.4483,
      0.6593,
      0.8194,
      0.9551
    ]
  ],
  "cl_metrics": {
    "accuracy": 0.38176,
    "forgetting": 0.6320555555555556,
    "bwt": -0.6320555555555556,
    "fwt": -0.09999999999999999,
    "plasticity": 0.95061
  },
  "computational_metrics": {
    "avg_task_time": 85.15990860462189,
    "total_training_time": 851.5990860462189
  },
  "history": [
    {
      "avg_loss": 0.31831055798653224,
      "final_loss": 0.2236997658517887,
      "avg_accuracy": 0.9118366666666666,
      "final_accuracy": 0.9361333333333334,
      "time_seconds": 59.61990976333618
    },
    {
      "avg_loss": 1.1456047688664466,
      "final_loss": 0.23892555539526028,
      "avg_accuracy": 0.7393833333333334,
      "final_accuracy": 0.9293833333333333,
      "time_seconds": 64.9610607624054
    },
    {
      "avg_loss": 0.2188273351290015,
      "final_loss": 0.16039747812314584,
      "avg_accuracy": 0.9357700000000001,
      "final_accuracy": 0.9533,
      "time_seconds": 71.15950679779053
    },
    {
      "avg_loss": 1.666963682585815,
      "final_loss": 0.19701795622722298,
      "avg_accuracy": 0.7330733333333332,
      "final_accuracy": 0.9416666666666667,
      "time_seconds": 76.04971051216125
    },
    {
      "avg_loss": 0.1952939332973188,
      "final_loss": 0.13801098689397198,
      "avg_accuracy": 0.9420999999999999,
      "final_accuracy": 0.9597833333333333,
      "time_seconds": 82.20733761787415
    },
    {
      "avg_loss": 1.4944791745390498,
      "final_loss": 0.17304894831110992,
      "avg_accuracy": 0.7285666666666667,
      "final_accuracy": 0.94765,
      "time_seconds": 88.67090916633606
    },
    {
      "avg_loss": 0.186585813441844,
      "final_loss": 0.12676028386036406,
      "avg_accuracy": 0.9445033333333333,
      "final_accuracy": 0.9630666666666666,
      "time_seconds": 93.35901856422424
    },
    {
      "avg_loss": 1.2729358208899908,
      "final_loss": 0.16600942924650494,
      "avg_accuracy": 0.7245533333333334,
      "final_accuracy": 0.9502166666666667,
      "time_seconds": 100.22920823097229
    },
    {
      "avg_loss": 0.17737893648286746,
      "final_loss": 0.11673140818916404,
      "avg_accuracy": 0.9465199999999999,
      "final_accuracy": 0.9654833333333334,
      "time_seconds": 105.53283143043518
    },
    {
      "avg_loss": 1.2525747402175975,
      "final_loss": 0.16397585532765016,
      "avg_accuracy": 0.7378633333333333,
      "final_accuracy": 0.9511833333333334,
      "time_seconds": 109.8095932006836
    }
  ],
  "epoch_accs": [
    [
      0.9136
    ],
    [
      0.9252
    ],
    [
      0.9312
    ],
    [
      0.9358
    ],
    [
      0.9364
    ],
    [
      0.9364,
      0.1504
    ],
    [
      0.9113,
      0.8867
    ],
    [
      0.9108,
      0.9146
    ],
    [
      0.8992,
      0.9275
    ],
    [
      0.8765,
      0.9375
    ],
    [
      0.7408,
      0.8779,
      0.9292
    ],
    [
      0.6223,
      0.8378,
      0.9439
    ],
    [
      0.5912,
      0.8076,
      0.9487
    ],
    [
      0.5301,
      0.7811,
      0.9501
    ],
    [
      0.5529,
      0.7945,
      0.9519
    ],
    [
      0.5529,
      0.7945,
      0.9519,
      0.0963
    ],
    [
      0.6522,
      0.8693,
      0.9116,
      0.8894
    ],
    [
      0.5905,
      0.8364,
      0.9116,
      0.9259
    ],
    [
      0.4731,
      0.773,
      0.8956,
      0.94
    ],
    [
      0.4022,
      0.6957,
      0.8586,
      0.9461
    ],
    [
      0.4245,
      0.5558,
      0.8176,
      0.9223,
      0.9386
    ],
    [
      0.3609,
      0.4674,
      0.7909,
      0.9116,
      0.946
    ],
    [
      0.3369,
      0.4713,
      0.7829,
      0.901,
      0.9527
    ],
    [
      0.3198,
      0.4423,
      0.7544,
      0.8955,
      0.9553
    ],
    [
      0.3261,
      0.4541,
      0.7636,
      0.8956,
      0.9565
    ],
    [
      0.3261,
      0.4541,
      0.7636,
      0.8956,
      0.9565,
      0.0932
    ],
    [
      0.3944,
      0.5296,
      0.7528,
      0.8462,
      0.9151,
      0.8816
    ],
    [
      0.3458,
      0.4718,
      0.7042,
      0.8268,
      0.9214,
      0.9309
    ],
    [
      0.3181,
      0.3937,
      0.6384,
      0.8029,
      0.9308,
      0.9444
    ],
    [
      0.3034,
      0.3701,
      0.5742,
      0.7703,
      0.9294,
      0.9525
    ],
    [
      0.2337,
      0.2468,
      0.4476,
      0.6458,
      0.8207,
      0.9059,
      0.9369
    ],
    [
      0.2074,
      0.2084,
      0.3969,
      0.5786,
      0.7914,
      0.8965,
      0.9502
    ],
    [
      0.1947,
      0.1951,
      0.3674,
      0.5186,
      0.7822,
      0.8908,
      0.956
    ],
    [
      0.1964,
      0.1897,
      0.3538,
      0.5008,
      0.7724,
      0.8855,
      0.957
    ],
    [
      0.1957,
      0.193,
      0.3588,
      0.5081,
      0.7726,
      0.8824,
      0.9573
    ],
    [
      0.1957,
      0.193,
      0.3588,
      0.5081,
      0.7726,
      0.8824,
      0.9573,
      0.0885
    ],
    [
      0.1796,
      0.2529,
      0.3269,
      0.5548,
      0.6423,
      0.8622,
      0.9324,
      0.8678
    ],
    [
      0.1525,
      0.2119,
      0.2604,
      0.4439,
      0.5663,
      0.8125,
      0.9298,
      0.9288
    ],
    [
      0.1382,
      0.1862,
      0.2207,
      0.3577,
      0.5155,
      0.7488,
      0.9055,
      0.9456
    ],
    [
      0.132,
      0.1657,
      0.1754,
      0.2978,
      0.4732,
      0.655,
      0.8566,
      0.9504
    ],
    [
      0.1123,
      0.1253,
      0.1542,
      0.2429,
      0.3384,
      0.4185,
      0.7197,
      0.8904,
      0.9422
    ],
    [
      0.0994,
      0.1251,
      0.1333,
      0.2358,
      0.3142,
      0.3951,
      0.6694,
      0.8901,
      0.9557
    ],
    [
      0.1034,
      0.1195,
      0.1337,
      0.2266,
      0.3049,
      0.3821,
      0.6472,
      0.8675,
      0.9589
    ],
    [
      0.1025,
      0.1221,
      0.1282,
      0.2161,
      0.2874,
      0.3623,
      0.6179,
      0.854,
      0.9611
    ],
    [
      0.1075,
      0.1198,
      0.1275,
      0.2245,
      0.2988,
      0.3798,
      0.6444,
      0.8642,
      0.9624
    ],
    [
      0.1075,
      0.1198,
      0.1275,
      0.2245,
      0.2988,
      0.3798,
      0.6444,
      0.8642,
      0.9624,
      0.134
    ],
    [
      0.1038,
      0.0971,
      0.1049,
      0.2581,
      0.3109,
      0.3925,
      0.6334,
      0.7938,
      0.9267,
      0.8754
    ],
    [
      0.092,
      0.1034,
      0.0984,
      0.2383,
      0.2681,
      0.3476,
      0.5468,
      0.7554,
      0.913,
      0.9258
    ],
    [
      0.0859,
      0.0878,
      0.0809,
      0.2183,
      0.2566,
      0.3156,
      0.4774,
      0.6975,
      0.8694,
      0.9465
    ],
    [
      0.0794,
      0.0865,
      0.0746,
      0.1869,
      0.2213,
      0.2868,
      0.4483,
      0.6593,
      0.8194,
      0.9551
    ]
  ]
}